emotion_engine/__init__.py
emotion_engine/database.py
emotion_engine/scene_manager.py
emotion_aware_narrative-0.1.3.dist-info/METADATA
emotion_aware_narrative-0.1.3.dist-info/WHEEL
emotion_aware_narrative-0.1.3.dist-info/top_level.txt
emotion_aware_narrative-0.1.3.dist-info/RECORD
