Metadata-Version: 2.4
Name: emotion-aware-narrative
Version: 0.1.3
Summary: An AI-powered emotion detection system for game narrative enhancement
Home-page: https://github.com/sanjthebest/Emotion-Aware-Narrative-Engine
Author: Sanjana Robbi
Author-email: sanjanarobbi123@gmail.com
License: MIT
Project-URL: Bug Reports, https://github.com/sanjthebest/Emotion-Aware-Narrative-Engine/issues
Project-URL: Source, https://github.com/sanjthebest/Emotion-Aware-Narrative-Engine
Keywords: emotion,nlp,game-development,ai,narrative
Classifier: Development Status :: 3 - Alpha
Classifier: Intended Audience :: Developers
Classifier: License :: OSI Approved :: MIT License
Classifier: Programming Language :: Python :: 3
Classifier: Programming Language :: Python :: 3.7
Classifier: Programming Language :: Python :: 3.8
Classifier: Programming Language :: Python :: 3.9
Classifier: Topic :: Games/Entertainment
Classifier: Topic :: Software Development :: Libraries :: Python Modules
Classifier: Topic :: Scientific/Engineering :: Artificial Intelligence
Requires-Python: >=3.7
Requires-Dist: transformers>=4.30.0
Requires-Dist: torch>=2.0.0
Requires-Dist: numpy>=1.21.0
Dynamic: author
Dynamic: author-email
Dynamic: classifier
Dynamic: description
Dynamic: description-content-type
Dynamic: home-page
Dynamic: keywords
Dynamic: license
Dynamic: project-url
Dynamic: requires-dist
Dynamic: requires-python
Dynamic: summary
